{"lands":{"autotiles":[],"floors":[{"k":[272,0,0,192,0],"v":{"t":[5,0]}},{"k":[272,0,0,196,0],"v":{"t":[5,0]}},{"k":[273,0,0,195,0],"v":{"t":[5,0]}},{"k":[274,0,0,194,0],"v":{"t":[5,0]}},{"k":[275,0,0,193,0],"v":{"t":[5,0]}},{"k":[276,0,0,192,0],"v":{"t":[5,0]}},{"k":[272,0,0,195,0],"v":{"t":[5,0]}},{"k":[273,0,0,194,0],"v":{"t":[5,0]}},{"k":[274,0,0,193,0],"v":{"t":[5,0]}},{"k":[275,0,0,192,0],"v":{"t":[5,0]}},{"k":[272,0,0,194,0],"v":{"t":[5,0]}},{"k":[273,0,0,193,0],"v":{"t":[5,0]}},{"k":[274,0,0,192,0],"v":{"t":[5,0]}},{"k":[272,0,0,193,0],"v":{"t":[5,0]}},{"k":[273,0,0,192,0],"v":{"t":[5,0]}},{"k":[272,0,0,200,0],"v":{"t":[5,0]}},{"k":[273,0,0,199,0],"v":{"t":[5,0]}},{"k":[274,0,0,198,0],"v":{"t":[5,0]}},{"k":[275,0,0,197,0],"v":{"t":[5,0]}},{"k":[276,0,0,196,0],"v":{"t":[5,0]}},{"k":[277,0,0,195,0],"v":{"t":[5,0]}},{"k":[278,0,0,194,0],"v":{"t":[5,0]}},{"k":[279,0,0,193,0],"v":{"t":[5,0]}},{"k":[280,0,0,192,0],"v":{"t":[5,0]}},{"k":[272,0,0,199,0],"v":{"t":[5,0]}},{"k":[273,0,0,198,0],"v":{"t":[5,0]}},{"k":[274,0,0,197,0],"v":{"t":[5,0]}},{"k":[275,0,0,196,0],"v":{"t":[5,0]}},{"k":[276,0,0,195,0],"v":{"t":[5,0]}},{"k":[277,0,0,194,0],"v":{"t":[5,0]}},{"k":[278,0,0,193,0],"v":{"t":[5,0]}},{"k":[279,0,0,192,0],"v":{"t":[5,0]}},{"k":[272,0,0,198,0],"v":{"t":[5,0]}},{"k":[273,0,0,197,0],"v":{"t":[5,0]}},{"k":[274,0,0,196,0],"v":{"t":[5,0]}},{"k":[275,0,0,195,0],"v":{"t":[5,0]}},{"k":[276,0,0,194,0],"v":{"t":[5,0]}},{"k":[277,0,0,193,0],"v":{"t":[5,0]}},{"k":[278,0,0,192,0],"v":{"t":[5,0]}},{"k":[272,0,0,197,0],"v":{"t":[5,0]}},{"k":[273,0,0,196,0],"v":{"t":[5,0]}},{"k":[274,0,0,195,0],"v":{"t":[5,0]}},{"k":[275,0,0,194,0],"v":{"t":[5,0]}},{"k":[276,0,0,193,0],"v":{"t":[5,0]}},{"k":[277,0,0,192,0],"v":{"t":[5,0]}},{"k":[272,0,0,204,0],"v":{"t":[5,0]}},{"k":[273,0,0,203,0],"v":{"t":[5,0]}},{"k":[274,0,0,202,0],"v":{"t":[5,0]}},{"k":[275,0,0,201,0],"v":{"t":[5,0]}},{"k":[276,0,0,200,0],"v":{"t":[5,0]}},{"k":[277,0,0,199,0],"v":{"t":[5,0]}},{"k":[278,0,0,198,0],"v":{"t":[5,0]}},{"k":[279,0,0,197,0],"v":{"t":[5,0]}},{"k":[280,0,0,196,0],"v":{"t":[5,0]}},{"k":[281,0,0,195,0],"v":{"t":[5,0]}},{"k":[282,0,0,194,0],"v":{"t":[5,0]}},{"k":[283,0,0,193,0],"v":{"t":[5,0]}},{"k":[284,0,0,192,0],"v":{"t":[5,0]}},{"k":[272,0,0,203,0],"v":{"t":[5,0]}},{"k":[273,0,0,202,0],"v":{"t":[5,0]}},{"k":[274,0,0,201,0],"v":{"t":[5,0]}},{"k":[275,0,0,200,0],"v":{"t":[5,0]}},{"k":[276,0,0,199,0],"v":{"t":[5,0]}},{"k":[277,0,0,198,0],"v":{"t":[5,0]}},{"k":[278,0,0,197,0],"v":{"t":[5,0]}},{"k":[279,0,0,196,0],"v":{"t":[5,0]}},{"k":[280,0,0,195,0],"v":{"t":[5,0]}},{"k":[281,0,0,194,0],"v":{"t":[5,0]}},{"k":[282,0,0,193,0],"v":{"t":[5,0]}},{"k":[283,0,0,192,0],"v":{"t":[5,0]}},{"k":[272,0,0,202,0],"v":{"t":[5,0]}},{"k":[273,0,0,201,0],"v":{"t":[5,0]}},{"k":[274,0,0,200,0],"v":{"t":[5,0]}},{"k":[275,0,0,199,0],"v":{"t":[5,0]}},{"k":[276,0,0,198,0],"v":{"t":[5,0]}},{"k":[277,0,0,197,0],"v":{"t":[5,0]}},{"k":[278,0,0,196,0],"v":{"t":[5,0]}},{"k":[279,0,0,195,0],"v":{"t":[5,0]}},{"k":[280,0,0,194,0],"v":{"t":[5,0]}},{"k":[281,0,0,193,0],"v":{"t":[5,0]}},{"k":[282,0,0,192,0],"v":{"t":[5,0]}},{"k":[272,0,0,201,0],"v":{"t":[5,0]}},{"k":[273,0,0,200,0],"v":{"t":[5,0]}},{"k":[274,0,0,199,0],"v":{"t":[5,0]}},{"k":[275,0,0,198,0],"v":{"t":[5,0]}},{"k":[276,0,0,197,0],"v":{"t":[5,0]}},{"k":[277,0,0,196,0],"v":{"t":[5,0]}},{"k":[278,0,0,195,0],"v":{"t":[5,0]}},{"k":[279,0,0,194,0],"v":{"t":[5,0]}},{"k":[280,0,0,193,0],"v":{"t":[5,0]}},{"k":[281,0,0,192,0],"v":{"t":[5,0]}},{"k":[273,0,0,207,0],"v":{"t":[5,0]}},{"k":[274,0,0,206,0],"v":{"t":[5,0]}},{"k":[275,0,0,205,0],"v":{"t":[5,0]}},{"k":[276,0,0,204,0],"v":{"t":[5,0]}},{"k":[277,0,0,203,0],"v":{"t":[5,0]}},{"k":[278,0,0,202,0],"v":{"t":[5,0]}},{"k":[279,0,0,201,0],"v":{"t":[5,0]}},{"k":[280,0,0,200,0],"v":{"t":[5,0]}},{"k":[281,0,0,199,0],"v":{"t":[5,0]}},{"k":[282,0,0,198,0],"v":{"t":[5,0]}},{"k":[283,0,0,197,0],"v":{"t":[5,0]}},{"k":[284,0,0,196,0],"v":{"t":[5,0]}},{"k":[285,0,0,195,0],"v":{"t":[5,0]}},{"k":[286,0,0,194,0],"v":{"t":[5,0]}},{"k":[287,0,0,193,0],"v":{"t":[5,0]}},{"k":[272,0,0,207,0],"v":{"t":[5,0]}},{"k":[273,0,0,206,0],"v":{"t":[5,0]}},{"k":[274,0,0,205,0],"v":{"t":[5,0]}},{"k":[275,0,0,204,0],"v":{"t":[5,0]}},{"k":[276,0,0,203,0],"v":{"t":[5,0]}},{"k":[277,0,0,202,0],"v":{"t":[5,0]}},{"k":[278,0,0,201,0],"v":{"t":[5,0]}},{"k":[279,0,0,200,0],"v":{"t":[5,0]}},{"k":[280,0,0,199,0],"v":{"t":[5,0]}},{"k":[281,0,0,198,0],"v":{"t":[5,0]}},{"k":[282,0,0,197,0],"v":{"t":[5,0]}},{"k":[283,0,0,196,0],"v":{"t":[5,0]}},{"k":[284,0,0,195,0],"v":{"t":[5,0]}},{"k":[285,0,0,194,0],"v":{"t":[5,0]}},{"k":[286,0,0,193,0],"v":{"t":[5,0]}},{"k":[287,0,0,192,0],"v":{"t":[5,0]}},{"k":[272,0,0,206,0],"v":{"t":[5,0]}},{"k":[273,0,0,205,0],"v":{"t":[5,0]}},{"k":[274,0,0,204,0],"v":{"t":[5,0]}},{"k":[275,0,0,203,0],"v":{"t":[5,0]}},{"k":[276,0,0,202,0],"v":{"t":[5,0]}},{"k":[277,0,0,201,0],"v":{"t":[5,0]}},{"k":[278,0,0,200,0],"v":{"t":[5,0]}},{"k":[279,0,0,199,0],"v":{"t":[5,0]}},{"k":[280,0,0,198,0],"v":{"t":[5,0]}},{"k":[281,0,0,197,0],"v":{"t":[5,0]}},{"k":[282,0,0,196,0],"v":{"t":[5,0]}},{"k":[283,0,0,195,0],"v":{"t":[5,0]}},{"k":[284,0,0,194,0],"v":{"t":[5,0]}},{"k":[285,0,0,193,0],"v":{"t":[5,0]}},{"k":[286,0,0,192,0],"v":{"t":[5,0]}},{"k":[272,0,0,205,0],"v":{"t":[5,0]}},{"k":[273,0,0,204,0],"v":{"t":[5,0]}},{"k":[274,0,0,203,0],"v":{"t":[5,0]}},{"k":[275,0,0,202,0],"v":{"t":[5,0]}},{"k":[276,0,0,201,0],"v":{"t":[5,0]}},{"k":[277,0,0,200,0],"v":{"t":[5,0]}},{"k":[278,0,0,199,0],"v":{"t":[5,0]}},{"k":[279,0,0,198,0],"v":{"t":[5,0]}},{"k":[280,0,0,197,0],"v":{"t":[5,0]}},{"k":[281,0,0,196,0],"v":{"t":[5,0]}},{"k":[282,0,0,195,0],"v":{"t":[5,0]}},{"k":[283,0,0,194,0],"v":{"t":[5,0]}},{"k":[284,0,0,193,0],"v":{"t":[5,0]}},{"k":[285,0,0,192,0],"v":{"t":[5,0]}},{"k":[277,0,0,207,0],"v":{"t":[5,0]}},{"k":[278,0,0,206,0],"v":{"t":[5,0]}},{"k":[279,0,0,205,0],"v":{"t":[5,0]}},{"k":[280,0,0,204,0],"v":{"t":[5,0]}},{"k":[281,0,0,203,0],"v":{"t":[5,0]}},{"k":[282,0,0,202,0],"v":{"t":[5,0]}},{"k":[283,0,0,201,0],"v":{"t":[5,0]}},{"k":[284,0,0,200,0],"v":{"t":[5,0]}},{"k":[285,0,0,199,0],"v":{"t":[5,0]}},{"k":[286,0,0,198,0],"v":{"t":[5,0]}},{"k":[287,0,0,197,0],"v":{"t":[5,0]}},{"k":[276,0,0,207,0],"v":{"t":[5,0]}},{"k":[277,0,0,206,0],"v":{"t":[5,0]}},{"k":[278,0,0,205,0],"v":{"t":[5,0]}},{"k":[279,0,0,204,0],"v":{"t":[5,0]}},{"k":[280,0,0,203,0],"v":{"t":[5,0]}},{"k":[281,0,0,202,0],"v":{"t":[5,0]}},{"k":[282,0,0,201,0],"v":{"t":[5,0]}},{"k":[283,0,0,200,0],"v":{"t":[5,0]}},{"k":[284,0,0,199,0],"v":{"t":[5,0]}},{"k":[285,0,0,198,0],"v":{"t":[5,0]}},{"k":[286,0,0,197,0],"v":{"t":[5,0]}},{"k":[287,0,0,196,0],"v":{"t":[5,0]}},{"k":[275,0,0,207,0],"v":{"t":[5,0]}},{"k":[276,0,0,206,0],"v":{"t":[5,0]}},{"k":[277,0,0,205,0],"v":{"t":[5,0]}},{"k":[278,0,0,204,0],"v":{"t":[5,0]}},{"k":[279,0,0,203,0],"v":{"t":[5,0]}},{"k":[280,0,0,202,0],"v":{"t":[5,0]}},{"k":[281,0,0,201,0],"v":{"t":[5,0]}},{"k":[282,0,0,200,0],"v":{"t":[5,0]}},{"k":[283,0,0,199,0],"v":{"t":[5,0]}},{"k":[284,0,0,198,0],"v":{"t":[5,0]}},{"k":[285,0,0,197,0],"v":{"t":[5,0]}},{"k":[286,0,0,196,0],"v":{"t":[5,0]}},{"k":[287,0,0,195,0],"v":{"t":[5,0]}},{"k":[274,0,0,207,0],"v":{"t":[5,0]}},{"k":[275,0,0,206,0],"v":{"t":[5,0]}},{"k":[276,0,0,205,0],"v":{"t":[5,0]}},{"k":[277,0,0,204,0],"v":{"t":[5,0]}},{"k":[278,0,0,203,0],"v":{"t":[5,0]}},{"k":[279,0,0,202,0],"v":{"t":[5,0]}},{"k":[280,0,0,201,0],"v":{"t":[5,0]}},{"k":[281,0,0,200,0],"v":{"t":[5,0]}},{"k":[282,0,0,199,0],"v":{"t":[5,0]}},{"k":[283,0,0,198,0],"v":{"t":[5,0]}},{"k":[284,0,0,197,0],"v":{"t":[5,0]}},{"k":[285,0,0,196,0],"v":{"t":[5,0]}},{"k":[286,0,0,195,0],"v":{"t":[5,0]}},{"k":[287,0,0,194,0],"v":{"t":[5,0]}},{"k":[281,0,0,207,0],"v":{"t":[5,0]}},{"k":[282,0,0,206,0],"v":{"t":[5,0]}},{"k":[283,0,0,205,0],"v":{"t":[5,0]}},{"k":[284,0,0,204,0],"v":{"t":[5,0]}},{"k":[285,0,0,203,0],"v":{"t":[5,0]}},{"k":[286,0,0,202,0],"v":{"t":[5,0]}},{"k":[287,0,0,201,0],"v":{"t":[5,0]}},{"k":[280,0,0,207,0],"v":{"t":[5,0]}},{"k":[281,0,0,206,0],"v":{"t":[5,0]}},{"k":[282,0,0,205,0],"v":{"t":[5,0]}},{"k":[283,0,0,204,0],"v":{"t":[5,0]}},{"k":[284,0,0,203,0],"v":{"t":[5,0]}},{"k":[285,0,0,202,0],"v":{"t":[5,0]}},{"k":[286,0,0,201,0],"v":{"t":[5,0]}},{"k":[287,0,0,200,0],"v":{"t":[5,0]}},{"k":[279,0,0,207,0],"v":{"t":[5,0]}},{"k":[280,0,0,206,0],"v":{"t":[5,0]}},{"k":[281,0,0,205,0],"v":{"t":[5,0]}},{"k":[282,0,0,204,0],"v":{"t":[5,0]}},{"k":[283,0,0,203,0],"v":{"t":[5,0]}},{"k":[284,0,0,202,0],"v":{"t":[5,0]}},{"k":[285,0,0,201,0],"v":{"t":[5,0]}},{"k":[286,0,0,200,0],"v":{"t":[5,0]}},{"k":[287,0,0,199,0],"v":{"t":[5,0]}},{"k":[278,0,0,207,0],"v":{"t":[5,0]}},{"k":[279,0,0,206,0],"v":{"t":[5,0]}},{"k":[280,0,0,205,0],"v":{"t":[5,0]}},{"k":[281,0,0,204,0],"v":{"t":[5,0]}},{"k":[282,0,0,203,0],"v":{"t":[5,0]}},{"k":[283,0,0,202,0],"v":{"t":[5,0]}},{"k":[284,0,0,201,0],"v":{"t":[5,0]}},{"k":[285,0,0,200,0],"v":{"t":[5,0]}},{"k":[286,0,0,199,0],"v":{"t":[5,0]}},{"k":[287,0,0,198,0],"v":{"t":[5,0]}},{"k":[285,0,0,207,0],"v":{"t":[5,0]}},{"k":[286,0,0,206,0],"v":{"t":[5,0]}},{"k":[287,0,0,205,0],"v":{"t":[5,0]}},{"k":[284,0,0,207,0],"v":{"t":[5,0]}},{"k":[285,0,0,206,0],"v":{"t":[5,0]}},{"k":[286,0,0,205,0],"v":{"t":[5,0]}},{"k":[287,0,0,204,0],"v":{"t":[5,0]}},{"k":[283,0,0,207,0],"v":{"t":[5,0]}},{"k":[284,0,0,206,0],"v":{"t":[5,0]}},{"k":[285,0,0,205,0],"v":{"t":[5,0]}},{"k":[286,0,0,204,0],"v":{"t":[5,0]}},{"k":[287,0,0,203,0],"v":{"t":[5,0]}},{"k":[282,0,0,207,0],"v":{"t":[5,0]}},{"k":[283,0,0,206,0],"v":{"t":[5,0]}},{"k":[284,0,0,205,0],"v":{"t":[5,0]}},{"k":[285,0,0,204,0],"v":{"t":[5,0]}},{"k":[286,0,0,203,0],"v":{"t":[5,0]}},{"k":[287,0,0,202,0],"v":{"t":[5,0]}},{"k":[287,0,0,207,0],"v":{"t":[5,0]}},{"k":[286,0,0,207,0],"v":{"t":[5,0]}},{"k":[287,0,0,206,0],"v":{"t":[5,0]}}]},"moun":{"a":[],"o":[]},"objs":{"list":[]},"objs3d":{"a":[],"o":[]},"sprites":{"list":[{"k":[282,0,0,204,0],"v":{"f":false,"k":5,"t":[6,9,2,3]}},{"k":[279,0,0,206,0],"v":{"f":false,"k":5,"t":[6,9,2,3]}},{"k":[279,0,0,194,0],"v":{"f":false,"k":5,"t":[6,9,2,3]}},{"k":[277,0,0,193,0],"v":{"f":false,"k":5,"t":[6,9,2,3]}},{"k":[279,0,0,205,0],"v":{"f":false,"k":5,"t":[6,9,2,3]}},{"k":[279,0,0,204,0],"v":{"f":false,"k":5,"t":[6,9,2,3]}},{"k":[280,0,0,207,0],"v":{"f":false,"k":5,"t":[6,9,2,3]}}],"overflow":[[272,0,0,208,0],[273,0,0,208,0],[280,0,0,208,0]],"walls":[]}}