{"lands":{"autotiles":[],"floors":[{"k":[272,0,0,76,0],"v":{"t":[5,0]}},{"k":[273,0,0,75,0],"v":{"t":[5,0]}},{"k":[274,0,0,74,0],"v":{"t":[5,0]}},{"k":[275,0,0,73,0],"v":{"t":[5,0]}},{"k":[276,0,0,72,0],"v":{"t":[5,0]}},{"k":[277,0,0,71,0],"v":{"t":[5,0]}},{"k":[278,0,0,70,0],"v":{"t":[5,0]}},{"k":[279,0,0,69,0],"v":{"t":[5,0]}},{"k":[280,0,0,68,0],"v":{"t":[5,0]}},{"k":[281,0,0,67,0],"v":{"t":[5,0]}},{"k":[282,0,0,66,0],"v":{"t":[5,0]}},{"k":[283,0,0,65,0],"v":{"t":[5,0]}},{"k":[284,0,0,64,0],"v":{"t":[5,0]}},{"k":[272,0,0,75,0],"v":{"t":[5,0]}},{"k":[273,0,0,74,0],"v":{"t":[5,0]}},{"k":[274,0,0,73,0],"v":{"t":[5,0]}},{"k":[275,0,0,72,0],"v":{"t":[5,0]}},{"k":[276,0,0,71,0],"v":{"t":[5,0]}},{"k":[277,0,0,70,0],"v":{"t":[5,0]}},{"k":[278,0,0,69,0],"v":{"t":[5,0]}},{"k":[279,0,0,68,0],"v":{"t":[5,0]}},{"k":[280,0,0,67,0],"v":{"t":[5,0]}},{"k":[281,0,0,66,0],"v":{"t":[5,0]}},{"k":[282,0,0,65,0],"v":{"t":[5,0]}},{"k":[283,0,0,64,0],"v":{"t":[5,0]}},{"k":[272,0,0,74,0],"v":{"t":[5,0]}},{"k":[273,0,0,73,0],"v":{"t":[5,0]}},{"k":[274,0,0,72,0],"v":{"t":[5,0]}},{"k":[275,0,0,71,0],"v":{"t":[5,0]}},{"k":[276,0,0,70,0],"v":{"t":[5,0]}},{"k":[277,0,0,69,0],"v":{"t":[5,0]}},{"k":[278,0,0,68,0],"v":{"t":[5,0]}},{"k":[279,0,0,67,0],"v":{"t":[5,0]}},{"k":[280,0,0,66,0],"v":{"t":[5,0]}},{"k":[281,0,0,65,0],"v":{"t":[5,0]}},{"k":[282,0,0,64,0],"v":{"t":[5,0]}},{"k":[272,0,0,73,0],"v":{"t":[5,0]}},{"k":[273,0,0,72,0],"v":{"t":[5,0]}},{"k":[274,0,0,71,0],"v":{"t":[5,0]}},{"k":[275,0,0,70,0],"v":{"t":[5,0]}},{"k":[276,0,0,69,0],"v":{"t":[5,0]}},{"k":[277,0,0,68,0],"v":{"t":[5,0]}},{"k":[278,0,0,67,0],"v":{"t":[5,0]}},{"k":[279,0,0,66,0],"v":{"t":[5,0]}},{"k":[280,0,0,65,0],"v":{"t":[5,0]}},{"k":[281,0,0,64,0],"v":{"t":[5,0]}},{"k":[273,0,0,79,0],"v":{"t":[5,0]}},{"k":[274,0,0,78,0],"v":{"t":[5,0]}},{"k":[275,0,0,77,0],"v":{"t":[5,0]}},{"k":[276,0,0,76,0],"v":{"t":[5,0]}},{"k":[277,0,0,75,0],"v":{"t":[5,0]}},{"k":[278,0,0,74,0],"v":{"t":[5,0]}},{"k":[279,0,0,73,0],"v":{"t":[5,0]}},{"k":[280,0,0,72,0],"v":{"t":[5,0]}},{"k":[281,0,0,71,0],"v":{"t":[5,0]}},{"k":[282,0,0,70,0],"v":{"t":[5,0]}},{"k":[283,0,0,69,0],"v":{"t":[5,0]}},{"k":[284,0,0,68,0],"v":{"t":[5,0]}},{"k":[285,0,0,67,0],"v":{"t":[5,0]}},{"k":[286,0,0,66,0],"v":{"t":[5,0]}},{"k":[287,0,0,65,0],"v":{"t":[5,0]}},{"k":[272,0,0,79,0],"v":{"t":[5,0]}},{"k":[273,0,0,78,0],"v":{"t":[5,0]}},{"k":[274,0,0,77,0],"v":{"t":[5,0]}},{"k":[275,0,0,76,0],"v":{"t":[5,0]}},{"k":[276,0,0,75,0],"v":{"t":[5,0]}},{"k":[277,0,0,74,0],"v":{"t":[5,0]}},{"k":[278,0,0,73,0],"v":{"t":[5,0]}},{"k":[279,0,0,72,0],"v":{"t":[5,0]}},{"k":[280,0,0,71,0],"v":{"t":[5,0]}},{"k":[281,0,0,70,0],"v":{"t":[5,0]}},{"k":[282,0,0,69,0],"v":{"t":[5,0]}},{"k":[283,0,0,68,0],"v":{"t":[5,0]}},{"k":[284,0,0,67,0],"v":{"t":[5,0]}},{"k":[285,0,0,66,0],"v":{"t":[5,0]}},{"k":[286,0,0,65,0],"v":{"t":[5,0]}},{"k":[287,0,0,64,0],"v":{"t":[5,0]}},{"k":[272,0,0,78,0],"v":{"t":[5,0]}},{"k":[273,0,0,77,0],"v":{"t":[5,0]}},{"k":[274,0,0,76,0],"v":{"t":[5,0]}},{"k":[275,0,0,75,0],"v":{"t":[5,0]}},{"k":[276,0,0,74,0],"v":{"t":[5,0]}},{"k":[277,0,0,73,0],"v":{"t":[5,0]}},{"k":[278,0,0,72,0],"v":{"t":[5,0]}},{"k":[279,0,0,71,0],"v":{"t":[5,0]}},{"k":[280,0,0,70,0],"v":{"t":[5,0]}},{"k":[281,0,0,69,0],"v":{"t":[5,0]}},{"k":[282,0,0,68,0],"v":{"t":[5,0]}},{"k":[283,0,0,67,0],"v":{"t":[5,0]}},{"k":[284,0,0,66,0],"v":{"t":[5,0]}},{"k":[285,0,0,65,0],"v":{"t":[5,0]}},{"k":[286,0,0,64,0],"v":{"t":[5,0]}},{"k":[272,0,0,77,0],"v":{"t":[5,0]}},{"k":[273,0,0,76,0],"v":{"t":[5,0]}},{"k":[274,0,0,75,0],"v":{"t":[5,0]}},{"k":[275,0,0,74,0],"v":{"t":[5,0]}},{"k":[276,0,0,73,0],"v":{"t":[5,0]}},{"k":[277,0,0,72,0],"v":{"t":[5,0]}},{"k":[278,0,0,71,0],"v":{"t":[5,0]}},{"k":[279,0,0,70,0],"v":{"t":[5,0]}},{"k":[280,0,0,69,0],"v":{"t":[5,0]}},{"k":[281,0,0,68,0],"v":{"t":[5,0]}},{"k":[282,0,0,67,0],"v":{"t":[5,0]}},{"k":[283,0,0,66,0],"v":{"t":[5,0]}},{"k":[284,0,0,65,0],"v":{"t":[5,0]}},{"k":[285,0,0,64,0],"v":{"t":[5,0]}},{"k":[277,0,0,79,0],"v":{"t":[5,0]}},{"k":[278,0,0,78,0],"v":{"t":[5,0]}},{"k":[279,0,0,77,0],"v":{"t":[5,0]}},{"k":[280,0,0,76,0],"v":{"t":[5,0]}},{"k":[281,0,0,75,0],"v":{"t":[5,0]}},{"k":[282,0,0,74,0],"v":{"t":[5,0]}},{"k":[283,0,0,73,0],"v":{"t":[5,0]}},{"k":[284,0,0,72,0],"v":{"t":[5,0]}},{"k":[285,0,0,71,0],"v":{"t":[5,0]}},{"k":[286,0,0,70,0],"v":{"t":[5,0]}},{"k":[287,0,0,69,0],"v":{"t":[5,0]}},{"k":[276,0,0,79,0],"v":{"t":[5,0]}},{"k":[277,0,0,78,0],"v":{"t":[5,0]}},{"k":[278,0,0,77,0],"v":{"t":[5,0]}},{"k":[279,0,0,76,0],"v":{"t":[5,0]}},{"k":[280,0,0,75,0],"v":{"t":[5,0]}},{"k":[281,0,0,74,0],"v":{"t":[5,0]}},{"k":[282,0,0,73,0],"v":{"t":[5,0]}},{"k":[283,0,0,72,0],"v":{"t":[5,0]}},{"k":[284,0,0,71,0],"v":{"t":[5,0]}},{"k":[285,0,0,70,0],"v":{"t":[5,0]}},{"k":[286,0,0,69,0],"v":{"t":[5,0]}},{"k":[287,0,0,68,0],"v":{"t":[5,0]}},{"k":[275,0,0,79,0],"v":{"t":[5,0]}},{"k":[276,0,0,78,0],"v":{"t":[5,0]}},{"k":[277,0,0,77,0],"v":{"t":[5,0]}},{"k":[278,0,0,76,0],"v":{"t":[5,0]}},{"k":[279,0,0,75,0],"v":{"t":[5,0]}},{"k":[280,0,0,74,0],"v":{"t":[5,0]}},{"k":[281,0,0,73,0],"v":{"t":[5,0]}},{"k":[282,0,0,72,0],"v":{"t":[5,0]}},{"k":[283,0,0,71,0],"v":{"t":[5,0]}},{"k":[284,0,0,70,0],"v":{"t":[5,0]}},{"k":[285,0,0,69,0],"v":{"t":[5,0]}},{"k":[286,0,0,68,0],"v":{"t":[5,0]}},{"k":[287,0,0,67,0],"v":{"t":[5,0]}},{"k":[274,0,0,79,0],"v":{"t":[5,0]}},{"k":[275,0,0,78,0],"v":{"t":[5,0]}},{"k":[276,0,0,77,0],"v":{"t":[5,0]}},{"k":[277,0,0,76,0],"v":{"t":[5,0]}},{"k":[278,0,0,75,0],"v":{"t":[5,0]}},{"k":[279,0,0,74,0],"v":{"t":[5,0]}},{"k":[280,0,0,73,0],"v":{"t":[5,0]}},{"k":[281,0,0,72,0],"v":{"t":[5,0]}},{"k":[282,0,0,71,0],"v":{"t":[5,0]}},{"k":[283,0,0,70,0],"v":{"t":[5,0]}},{"k":[284,0,0,69,0],"v":{"t":[5,0]}},{"k":[285,0,0,68,0],"v":{"t":[5,0]}},{"k":[286,0,0,67,0],"v":{"t":[5,0]}},{"k":[287,0,0,66,0],"v":{"t":[5,0]}},{"k":[281,0,0,79,0],"v":{"t":[5,0]}},{"k":[282,0,0,78,0],"v":{"t":[5,0]}},{"k":[283,0,0,77,0],"v":{"t":[5,0]}},{"k":[284,0,0,76,0],"v":{"t":[5,0]}},{"k":[285,0,0,75,0],"v":{"t":[5,0]}},{"k":[286,0,0,74,0],"v":{"t":[5,0]}},{"k":[287,0,0,73,0],"v":{"t":[5,0]}},{"k":[280,0,0,79,0],"v":{"t":[5,0]}},{"k":[281,0,0,78,0],"v":{"t":[5,0]}},{"k":[282,0,0,77,0],"v":{"t":[5,0]}},{"k":[283,0,0,76,0],"v":{"t":[5,0]}},{"k":[284,0,0,75,0],"v":{"t":[5,0]}},{"k":[285,0,0,74,0],"v":{"t":[5,0]}},{"k":[286,0,0,73,0],"v":{"t":[5,0]}},{"k":[287,0,0,72,0],"v":{"t":[5,0]}},{"k":[279,0,0,79,0],"v":{"t":[5,0]}},{"k":[280,0,0,78,0],"v":{"t":[5,0]}},{"k":[281,0,0,77,0],"v":{"t":[5,0]}},{"k":[282,0,0,76,0],"v":{"t":[5,0]}},{"k":[283,0,0,75,0],"v":{"t":[5,0]}},{"k":[284,0,0,74,0],"v":{"t":[5,0]}},{"k":[285,0,0,73,0],"v":{"t":[5,0]}},{"k":[286,0,0,72,0],"v":{"t":[5,0]}},{"k":[287,0,0,71,0],"v":{"t":[5,0]}},{"k":[278,0,0,79,0],"v":{"t":[5,0]}},{"k":[279,0,0,78,0],"v":{"t":[5,0]}},{"k":[280,0,0,77,0],"v":{"t":[5,0]}},{"k":[281,0,0,76,0],"v":{"t":[5,0]}},{"k":[282,0,0,75,0],"v":{"t":[5,0]}},{"k":[283,0,0,74,0],"v":{"t":[5,0]}},{"k":[284,0,0,73,0],"v":{"t":[5,0]}},{"k":[285,0,0,72,0],"v":{"t":[5,0]}},{"k":[286,0,0,71,0],"v":{"t":[5,0]}},{"k":[287,0,0,70,0],"v":{"t":[5,0]}},{"k":[285,0,0,79,0],"v":{"t":[5,0]}},{"k":[286,0,0,78,0],"v":{"t":[5,0]}},{"k":[287,0,0,77,0],"v":{"t":[5,0]}},{"k":[284,0,0,79,0],"v":{"t":[5,0]}},{"k":[285,0,0,78,0],"v":{"t":[5,0]}},{"k":[286,0,0,77,0],"v":{"t":[5,0]}},{"k":[287,0,0,76,0],"v":{"t":[5,0]}},{"k":[283,0,0,79,0],"v":{"t":[5,0]}},{"k":[284,0,0,78,0],"v":{"t":[5,0]}},{"k":[285,0,0,77,0],"v":{"t":[5,0]}},{"k":[286,0,0,76,0],"v":{"t":[5,0]}},{"k":[287,0,0,75,0],"v":{"t":[5,0]}},{"k":[282,0,0,79,0],"v":{"t":[5,0]}},{"k":[283,0,0,78,0],"v":{"t":[5,0]}},{"k":[284,0,0,77,0],"v":{"t":[5,0]}},{"k":[285,0,0,76,0],"v":{"t":[5,0]}},{"k":[286,0,0,75,0],"v":{"t":[5,0]}},{"k":[287,0,0,74,0],"v":{"t":[5,0]}},{"k":[287,0,0,79,0],"v":{"t":[5,0]}},{"k":[286,0,0,79,0],"v":{"t":[5,0]}},{"k":[287,0,0,78,0],"v":{"t":[5,0]}},{"k":[272,0,0,64,0],"v":{"t":[5,0]}},{"k":[272,0,0,68,0],"v":{"t":[5,0]}},{"k":[273,0,0,67,0],"v":{"t":[5,0]}},{"k":[274,0,0,66,0],"v":{"t":[5,0]}},{"k":[275,0,0,65,0],"v":{"t":[5,0]}},{"k":[276,0,0,64,0],"v":{"t":[5,0]}},{"k":[272,0,0,67,0],"v":{"t":[5,0]}},{"k":[273,0,0,66,0],"v":{"t":[5,0]}},{"k":[274,0,0,65,0],"v":{"t":[5,0]}},{"k":[275,0,0,64,0],"v":{"t":[5,0]}},{"k":[272,0,0,66,0],"v":{"t":[5,0]}},{"k":[273,0,0,65,0],"v":{"t":[5,0]}},{"k":[274,0,0,64,0],"v":{"t":[5,0]}},{"k":[272,0,0,65,0],"v":{"t":[5,0]}},{"k":[273,0,0,64,0],"v":{"t":[5,0]}},{"k":[272,0,0,72,0],"v":{"t":[5,0]}},{"k":[273,0,0,71,0],"v":{"t":[5,0]}},{"k":[274,0,0,70,0],"v":{"t":[5,0]}},{"k":[275,0,0,69,0],"v":{"t":[5,0]}},{"k":[276,0,0,68,0],"v":{"t":[5,0]}},{"k":[277,0,0,67,0],"v":{"t":[5,0]}},{"k":[278,0,0,66,0],"v":{"t":[5,0]}},{"k":[279,0,0,65,0],"v":{"t":[5,0]}},{"k":[280,0,0,64,0],"v":{"t":[5,0]}},{"k":[272,0,0,71,0],"v":{"t":[5,0]}},{"k":[273,0,0,70,0],"v":{"t":[5,0]}},{"k":[274,0,0,69,0],"v":{"t":[5,0]}},{"k":[275,0,0,68,0],"v":{"t":[5,0]}},{"k":[276,0,0,67,0],"v":{"t":[5,0]}},{"k":[277,0,0,66,0],"v":{"t":[5,0]}},{"k":[278,0,0,65,0],"v":{"t":[5,0]}},{"k":[279,0,0,64,0],"v":{"t":[5,0]}},{"k":[272,0,0,70,0],"v":{"t":[5,0]}},{"k":[273,0,0,69,0],"v":{"t":[5,0]}},{"k":[274,0,0,68,0],"v":{"t":[5,0]}},{"k":[275,0,0,67,0],"v":{"t":[5,0]}},{"k":[276,0,0,66,0],"v":{"t":[5,0]}},{"k":[277,0,0,65,0],"v":{"t":[5,0]}},{"k":[278,0,0,64,0],"v":{"t":[5,0]}},{"k":[272,0,0,69,0],"v":{"t":[5,0]}},{"k":[273,0,0,68,0],"v":{"t":[5,0]}},{"k":[274,0,0,67,0],"v":{"t":[5,0]}},{"k":[275,0,0,66,0],"v":{"t":[5,0]}},{"k":[276,0,0,65,0],"v":{"t":[5,0]}},{"k":[277,0,0,64,0],"v":{"t":[5,0]}}]},"moun":{"a":[],"o":[]},"objs":{"list":[]},"objs3d":{"a":[],"o":[]},"sprites":{"list":[],"overflow":[],"walls":[]}}